{
    "req_before_use": {
        "authorize_scope": [],
        "sensi_apis": [
            "wx.getUserInfo",
            "wx.getUserInfo"
        ],
        "violation_page": [
            "app.js",
            "app.js",
            "/root/minidroid/dataset/miniprograms/wxa41a25c0d8c698ab/pages/index/index"
        ]
    },
    "blanket_reqs": {
        "authorize_scope": [],
        "sensi_apis": [
            "wx.getUserInfo",
            "wx.getUserInfo"
        ],
        "violation_page": [
            "app.js",
            "app.js",
            "/root/minidroid/dataset/miniprograms/wxa41a25c0d8c698ab/pages/index/index"
        ]
    },
    "compulsory_req": null
}